actuator_ai/__init__.py
actuator_ai/cli.py
actuator_ai/api/__init__.py
actuator_ai/api/app.py
actuator_ai/core/__init__.py
actuator_ai/core/decorators.py
actuator_ai/core/llm_adapter.py
actuator_ai/core/patterns.py
actuator_ai/core/registry.py
actuator_ai/examples/__init__.py
actuator_ai/examples/weather_bot/__init__.py
actuator_ai/examples/weather_bot/actions.py
actuator_ai/examples/weather_bot/formatters.py
actuator_ai/examples/weather_bot/main.py
actuator_ai-0.1.0.dist-info/LICENSE
actuator_ai-0.1.0.dist-info/METADATA
actuator_ai-0.1.0.dist-info/WHEEL
actuator_ai-0.1.0.dist-info/entry_points.txt
actuator_ai-0.1.0.dist-info/top_level.txt
actuator_ai-0.1.0.dist-info/RECORD
