Metadata-Version: 2.2
Name: actuator-ai
Version: 0.1.0
Summary: A framework for building natural language interfaces to actions
Home-page: https://github.com/yourusername/actuator-ai
Author: Umair Haider
Author-email: your.email@example.com
Classifier: Programming Language :: Python :: 3
Classifier: License :: OSI Approved :: MIT License
Classifier: Operating System :: OS Independent
Classifier: Development Status :: 4 - Beta
Classifier: Intended Audience :: Developers
Classifier: Topic :: Software Development :: Libraries :: Application Frameworks
Classifier: Topic :: Scientific/Engineering :: Artificial Intelligence
Requires-Python: >=3.8
License-File: LICENSE
Requires-Dist: fastapi==0.115.11
Requires-Dist: uvicorn==0.34.0
Requires-Dist: pydantic==2.10.6
Requires-Dist: langchain==0.3.20
Requires-Dist: langchain-community==0.3.19
Requires-Dist: openai==1.65.5
Requires-Dist: python-dotenv==1.0.1
Provides-Extra: dev
Requires-Dist: pytest>=7.0.0; extra == "dev"
Requires-Dist: black>=23.0.0; extra == "dev"
Requires-Dist: isort>=5.12.0; extra == "dev"
Requires-Dist: flake8>=6.0.0; extra == "dev"
Requires-Dist: mypy>=1.0.0; extra == "dev"
Dynamic: author
Dynamic: author-email
Dynamic: classifier
Dynamic: description
Dynamic: description-content-type
Dynamic: home-page
Dynamic: provides-extra
Dynamic: requires-dist
Dynamic: requires-python
Dynamic: summary
